totalface_cpu/__init__.py
totalface_cpu/bbox_anchor.py
totalface_cpu/get_config.py
totalface_cpu/print_info.py
totalface_cpu/data/__init__.py
totalface_cpu/data/constant.py
totalface_cpu/data/image.py
totalface_cpu/data/experiments/__init__.py
totalface_cpu/data/experiments/AFLW/__init__.py
totalface_cpu/data/experiments/AFLW/pip_32_16_60_r18_l2_l1_10_1_nb10.py
totalface_cpu/data/experiments/COFW/__init__.py
totalface_cpu/data/experiments/COFW/pip_32_16_60_r18_l2_l1_10_1_nb10.py
totalface_cpu/data/experiments/WFLW/__init__.py
totalface_cpu/data/experiments/WFLW/pip_32_16_60_mv3_large_l2_l1_10_1_nb10.py
totalface_cpu/data/experiments/WFLW/pip_32_16_60_mv3_small_l2_l1_10_1_nb10.py
totalface_cpu/data/experiments/WFLW/pip_32_16_60_r18_l2_l1_10_1_nb10.py
totalface_cpu/data/experiments/data_300W/__init__.py
totalface_cpu/data/experiments/data_300W/pip_32_16_60_r18_l2_l1_10_1_nb10.py
totalface_cpu/face/__init__.py
totalface_cpu/face/blur.py
totalface_cpu/face/common.py
totalface_cpu/face/get_result.py
totalface_cpu/model_zoo/__init__.py
totalface_cpu/model_zoo/get_models.py
totalface_cpu/model_zoo/backbones/__init__.py
totalface_cpu/model_zoo/backbones/efficientNet.py
totalface_cpu/model_zoo/backbones/groupface.py
totalface_cpu/model_zoo/backbones/iresnet.py
totalface_cpu/model_zoo/backbones/mobilefacenet.py
totalface_cpu/model_zoo/backbones/net.py
totalface_cpu/model_zoo/backbones/race_linear.py
totalface_cpu/model_zoo/backbones/retinaface.py
totalface_cpu/model_zoo/model_attribute/__init__.py
totalface_cpu/model_zoo/model_attribute/arcface_GenderAge.py
totalface_cpu/model_zoo/model_attribute/arcface_Race.py
totalface_cpu/model_zoo/model_attribute/expression.py
totalface_cpu/model_zoo/model_attribute/liveness.py
totalface_cpu/model_zoo/model_attribute/mask_detector.py
totalface_cpu/model_zoo/model_common/__init__.py
totalface_cpu/model_zoo/model_common/load_onnx.py
totalface_cpu/model_zoo/model_common/load_openvino.py
totalface_cpu/model_zoo/model_detection/__init__.py
totalface_cpu-0.0.3.dist-info/METADATA
totalface_cpu-0.0.3.dist-info/WHEEL
totalface_cpu-0.0.3.dist-info/top_level.txt
totalface_cpu-0.0.3.dist-info/RECORD
