Metadata-Version: 2.1
Name: totalface-cpu
Version: 0.0.3
Summary: totalface cpu package
Author: lululalamm
Author-email: yms2109@gmail.com
Requires-Python: >=3
